napari_ccp4map/__init__.py
napari_ccp4map/_reader.py
napari_ccp4map-1.0.dist-info/LICENSE
napari_ccp4map-1.0.dist-info/METADATA
napari_ccp4map-1.0.dist-info/WHEEL
napari_ccp4map-1.0.dist-info/entry_points.txt
napari_ccp4map-1.0.dist-info/top_level.txt
napari_ccp4map-1.0.dist-info/RECORD
