Metadata-Version: 2.1
Name: napari-ccp4map
Version: 1.0
Summary: Enables napari to read .map files in the ccp4 format. Drag&Drop or press Ctrl+O to read files.
Home-page: https://github.com/biberger/napari-ccp4map
Author: Simon Biberger
Author-email: dev@biberger.xyz
License: BSD-3-Clause
Project-URL: Bug Tracker, https://github.com/biberger/napari-ccp4map/issues
Project-URL: Documentation, https://github.com/biberger/napari-ccp4map#README.md
Project-URL: Source Code, https://github.com/biberger/napari-ccp4map
Project-URL: User Support, https://github.com/biberger/napari-ccp4map/issues
Platform: UNKNOWN
Classifier: Development Status :: 2 - Pre-Alpha
Classifier: Intended Audience :: Developers
Classifier: Framework :: napari
Classifier: Topic :: Software Development :: Testing
Classifier: Programming Language :: Python
Classifier: Programming Language :: Python :: 3
Classifier: Programming Language :: Python :: 3.7
Classifier: Programming Language :: Python :: 3.8
Classifier: Programming Language :: Python :: 3.9
Classifier: Operating System :: OS Independent
Classifier: License :: OSI Approved :: BSD License
Requires-Python: >=3.7
License-File: LICENSE
Requires-Dist: napari-plugin-engine (>=0.1.4)
Requires-Dist: numpy
Requires-Dist: gemmi
